calli_inter/__init__.py
calli_inter/interface.py
calli_inter-0.0.5.dist-info/METADATA
calli_inter-0.0.5.dist-info/WHEEL
calli_inter-0.0.5.dist-info/licenses/LICENSE
calli_inter-0.0.5.dist-info/RECORD
