Metadata-Version: 2.3
Name: calli_inter
Version: 0.0.5
Summary: Calliope mini as Interface for communication between computers
Project-URL: Homepage, https://github.com/inf-schule/calli-inter
Project-URL: Issues, https://github.com/inf-schule/calli-inter/issues
Author-email: Michael Becker <mich@elbecker.de>
License-File: LICENSE
Classifier: License :: OSI Approved :: MIT License
Classifier: Operating System :: OS Independent
Classifier: Programming Language :: Python :: 3
Requires-Python: >=3.8
Requires-Dist: pyserial<4.0,>=3.5
